aidefense/__init__.py
aidefense/cli.py
aidefense/config.py
aidefense/core.py
aidefense/exporters.py
aidefense/models.py
aidefense/prompts.py
aidefense/repl.py
aidefense/storage.py
aidefense/providers/__init__.py
aidefense/providers/base.py
aidefense/providers/moonshot.py
aidefense/providers/openai_compat.py
aidefense_cli-0.1.0.dist-info/licenses/LICENSE
aidefense_cli-0.1.0.dist-info/METADATA
aidefense_cli-0.1.0.dist-info/WHEEL
aidefense_cli-0.1.0.dist-info/entry_points.txt
aidefense_cli-0.1.0.dist-info/top_level.txt
aidefense_cli-0.1.0.dist-info/RECORD
