Metadata-Version: 2.4
Name: aidefense-cli
Version: 0.1.0
Summary: AI导论编程题的出题与答辩命令行工具（默认 Moonshot/Kimi）
Author: Sean
License-Expression: MIT
Project-URL: Homepage, https://github.com/<owner>/<repo>
Project-URL: Source, https://github.com/<owner>/<repo>
Project-URL: Issues, https://github.com/<owner>/<repo>/issues
Keywords: llm,cli,education,moonshot,kimi
Classifier: Development Status :: 3 - Alpha
Classifier: Environment :: Console
Classifier: Intended Audience :: Education
Classifier: Operating System :: OS Independent
Classifier: Programming Language :: Python :: 3
Classifier: Programming Language :: Python :: 3 :: Only
Classifier: Programming Language :: Python :: 3.9
Classifier: Programming Language :: Python :: 3.10
Classifier: Programming Language :: Python :: 3.11
Classifier: Programming Language :: Python :: 3.12
Classifier: Programming Language :: Python :: 3.13
Classifier: Topic :: Education
Requires-Python: >=3.9
License-File: LICENSE
Requires-Dist: prompt_toolkit>=3.0.43
Requires-Dist: requests>=2.31.0
Dynamic: license-file
